puppetdb_exporter/__init__.py
puppetdb_exporter/config.py
puppetdb_exporter/metrics.py
puppetdb_exporter/node.py
puppetdb_exporter/puppetdb.py
puppetdb_exporter-1.0.2.dist-info/METADATA
puppetdb_exporter-1.0.2.dist-info/WHEEL
puppetdb_exporter-1.0.2.dist-info/entry_points.txt
puppetdb_exporter-1.0.2.dist-info/top_level.txt
puppetdb_exporter-1.0.2.dist-info/RECORD
